LICENSE.txt
MANIFEST.in
README.md
requirements.txt
requirements_test.txt
setup.py
newrelic_alerting/__init__.py
newrelic_alerting/alert_manager.py
newrelic_alerting/api.py
newrelic_alerting/config.py
newrelic_alerting/exceptions.py
newrelic_alerting/helper.py
newrelic_alerting/pagination.py
newrelic_alerting/policy.py
newrelic_alerting/run.py
newrelic_alerting/server.py
newrelic_alerting/static/styles/index.css
newrelic_alerting/templates/index.html.j2
newrelic_alerts_manager.egg-info/PKG-INFO
newrelic_alerts_manager.egg-info/SOURCES.txt
newrelic_alerts_manager.egg-info/dependency_links.txt
newrelic_alerts_manager.egg-info/entry_points.txt
newrelic_alerts_manager.egg-info/requires.txt
newrelic_alerts_manager.egg-info/top_level.txt