Metadata-Version: 1.1
Name: newrelic-alerts-manager
Version: 0.0.9
Summary: Utility to keep newrelic server policies update via a configuration manifest
Home-page: https://github.com/SpringerPE/newrelic-alerts-manager
Author: Claudio Benfatto
Author-email: claudio.benfatto@springer.com
License: MIT
Download-URL: https://github.com/SpringerPE/newrelic-alerts-manager/releases/tag/v0.0.9
Keywords: newrelic alerts alerting
Platform: UNKNOWN
Classifier: Development Status :: 3 - Alpha
Classifier: Intended Audience :: System Administrators
Classifier: Topic :: System :: Systems Administration
Classifier: License :: OSI Approved :: MIT License
Classifier: Programming Language :: Python :: 3
